pipecat_anannas/__init__.py
pipecat_anannas/llm.py
pipecat_anannas-0.1.0.dist-info/licenses/LICENSE
pipecat_anannas-0.1.0.dist-info/METADATA
pipecat_anannas-0.1.0.dist-info/WHEEL
pipecat_anannas-0.1.0.dist-info/top_level.txt
pipecat_anannas-0.1.0.dist-info/RECORD
