Metadata-Version: 2.4
Name: pipecat-anannas
Version: 0.1.0
Summary: Anannas AI LLM integration for Pipecat - Access 500+ models through a unified gateway
Author-email: Anannas AI <support@anannas.ai>
License: BSD-2-Clause
Project-URL: Homepage, https://anannas.ai
Project-URL: Documentation, https://docs.anannas.ai
Project-URL: Repository, https://github.com/upsurgeio/anannas-pipecat-integration
Project-URL: Bug Tracker, https://github.com/upsurgeio/anannas-pipecat-integration/issues
Keywords: pipecat,anannas,llm,ai,voice,conversational-ai
Classifier: Development Status :: 4 - Beta
Classifier: Intended Audience :: Developers
Classifier: License :: OSI Approved :: BSD License
Classifier: Programming Language :: Python :: 3
Classifier: Programming Language :: Python :: 3.10
Classifier: Programming Language :: Python :: 3.11
Classifier: Programming Language :: Python :: 3.12
Classifier: Topic :: Software Development :: Libraries :: Python Modules
Classifier: Topic :: Scientific/Engineering :: Artificial Intelligence
Requires-Python: >=3.10
License-File: LICENSE
Requires-Dist: pipecat-ai>=0.0.86
Requires-Dist: openai>=1.0.0
Requires-Dist: loguru>=0.7.0
Provides-Extra: dev
Requires-Dist: pytest>=7.0; extra == "dev"
Requires-Dist: ruff>=0.1.0; extra == "dev"
Dynamic: license-file
